exoticst/__init__.py
exoticst/ac_automation.py
exoticst/bit.py
exoticst/dijkstra_shortest_path.py
exoticst/full_bin_tree_for_rmq.py
exoticst/heap_with_update.py
exoticst-1.3.3.dist-info/DESCRIPTION.rst
exoticst-1.3.3.dist-info/METADATA
exoticst-1.3.3.dist-info/RECORD
exoticst-1.3.3.dist-info/WHEEL
exoticst-1.3.3.dist-info/metadata.json
exoticst-1.3.3.dist-info/top_level.txt
tests/__init__.py
tests/test__rmq.py
tests/test_automaton.py
tests/test_bit.py
tests/test_dijkstra_search.py
tests/test_updatable_heap.py
