Metadata-Version: 2.0
Name: exoticst
Version: 1.3.3
Summary: Data structures, either not present in standard Python libs or are asymptotically more efficient
Home-page: https://github.com/valginer0/exotic-structures.git
Author: Val Giner
Author-email: valginer0@gmail.com
License: UNKNOWN
Platform: UNKNOWN
Classifier: Programming Language :: Python :: 3
Classifier: License :: OSI Approved :: MIT License
Classifier: Operating System :: OS Independent
